{
  "metadata": {
    "exportTime": "2026-01-26 22:53:36",
    "sceneName": "anothersimpletest",
    "totalObjects": 5,
    "toolVersion": "1.0"
  },
  "objects": [
    {
      "name": "Cube",
      "type": "other"
      ,"position": {
        "x": 0.00,
        "y": 0.00,
        "z": 0.00
      }
      ,"rotation": {
        "x": 0.00,
        "y": 0.00,
        "z": 0.00
      }
      ,"scale": {
        "x": 1.00,
        "y": 1.00,
        "z": 1.00
      }
    },
    {
      "name": "Directional Light",
      "type": "light"
      ,"position": {
        "x": 0.00,
        "y": 3.00,
        "z": 0.00
      }
      ,"rotation": {
        "x": 50.00,
        "y": 330.00,
        "z": 0.00
      }
      ,"scale": {
        "x": 1.00,
        "y": 1.00,
        "z": 1.00
      }
    },
    {
      "name": "Main Camera",
      "type": "camera"
      ,"position": {
        "x": 0.00,
        "y": 1.00,
        "z": -10.00
      }
      ,"rotation": {
        "x": 0.00,
        "y": 0.00,
        "z": 0.00
      }
      ,"scale": {
        "x": 1.00,
        "y": 1.00,
        "z": 1.00
      }
    },
    {
      "name": "Plane",
      "type": "other"
      ,"position": {
        "x": 0.00,
        "y": 0.00,
        "z": 0.00
      }
      ,"rotation": {
        "x": 0.00,
        "y": 0.00,
        "z": 0.00
      }
      ,"scale": {
        "x": 1.00,
        "y": 1.00,
        "z": 1.00
      }
    },
    {
      "name": "Sphere",
      "type": "other"
      ,"position": {
        "x": 0.00,
        "y": 0.00,
        "z": 0.00
      }
      ,"rotation": {
        "x": 0.00,
        "y": 0.00,
        "z": 0.00
      }
      ,"scale": {
        "x": 1.00,
        "y": 1.00,
        "z": 1.00
      }
    }
  ]
}
